bsch/__init__.py
bsch/gtc400c/__init__.py
bsch/gtc400c/colormaps.py
bsch/gtc400c/ftp.py
bsch/gtc400c/fusion.py
bsch/gtc400c/jpeg.py
bsch/gtc400c/metadata.py
bsch/gtc400c/util.py
bsch-1.0.5.dist-info/METADATA
bsch-1.0.5.dist-info/WHEEL
bsch-1.0.5.dist-info/entry_points.txt
bsch-1.0.5.dist-info/top_level.txt
bsch-1.0.5.dist-info/zip-safe
bsch-1.0.5.dist-info/RECORD
