Metadata-Version: 2.1
Name: bsch
Version: 1.0.5
Summary: Utilities and Python package for the Bosch GTC 400C (and more Bosch tools).
Home-page: https://github.com/pklaus/bsch
Author: Philipp Klaus
Author-email: philipp.l.klaus@web.de
License: GPL
Keywords: binary,time series,file,storage
Platform: any
Classifier: Development Status :: 4 - Beta
Classifier: Operating System :: OS Independent
Classifier: License :: OSI Approved :: GNU General Public License v3 or later (GPLv3+)
Classifier: Programming Language :: Python
Classifier: Programming Language :: Python :: 3
Classifier: Topic :: System :: Archiving :: Compression
Classifier: Topic :: Office/Business :: Financial
Classifier: Topic :: Scientific/Engineering
Requires-Dist: typing ; python_version < "3.5"
Provides-Extra: plotting
Requires-Dist: numpy ; extra == 'plotting'
Requires-Dist: Pillow ; extra == 'plotting'
Requires-Dist: matplotlib ; extra == 'plotting'
